RPA/Assistant/__init__.py
RPA/Assistant/background_flet.py
RPA/Assistant/callback_runner.py
RPA/Assistant/flet_client.py
RPA/Assistant/library.py
RPA/Assistant/types.py
RPA/Assistant/utils.py
rpaframework_assistant-3.0.6.dist-info/LICENSE
rpaframework_assistant-3.0.6.dist-info/METADATA
rpaframework_assistant-3.0.6.dist-info/WHEEL
rpaframework_assistant-3.0.6.dist-info/RECORD
